COPYING.txt
MANIFEST.in
README.txt
ez_setup.py
mini_pos.py
setup.py
miniPOS.egg-info/PKG-INFO
miniPOS.egg-info/SOURCES.txt
miniPOS.egg-info/dependency_links.txt
miniPOS.egg-info/top_level.txt
mpos/__init__.py
mpos/app_main.py
mpos/config.py
mpos/db_create.py
mpos/dlg_about.py
mpos/dlg_add.py
mpos/dlg_cal.py
mpos/dlg_edit.py
mpos/dlg_pos_addItem.py
mpos/frame_main.py
mpos/lang.py
mpos/lang_utility.py
mpos/lc_mpos.py
mpos/menu.py
mpos/mpos_db.py
mpos/mpos_print.py
mpos/mpos_utility.py
mpos/pnl_intro.py
mpos/pnl_inv.py
mpos/pnl_lang.py
mpos/pnl_pos.py
mpos/pnl_sales.py
mpos/prefs.py
mpos/resources/Armenian.csv
mpos/resources/English.csv
mpos/resources/French.csv
mpos/resources/Russian.csv
mpos/resources/Spanish.csv
mpos/resources/about.txt
mpos/resources/config.csv
mpos/resources/miniPOS.ico
mpos/resources/miniPOS.png
mpos/resources/miniPOS.svg
mpos/resources/pos_data.db