Metadata-Version: 1.0
Name: miniPOS
Version: 1.1
Summary: A simple POS program for record keeping.
Home-page: http://sourceforge.net/projects/minipos
Author: Gregory Wilson
Author-email: gwilson.sq1@gmail.com
License: GPL3
Platform: Any
Classifier: Development Status :: 4 - Beta
Classifier: Intended Audience :: End Users/Desktop
Classifier: License :: OSI Approved :: GNU General Public License (GPL)
Classifier: Operating System :: OS Independent
Classifier: Programming Language :: Python :: 2.7
Classifier: Topic :: Office/Business :: Financial :: Point-Of-Sale
Classifier: Topic :: Office/Business
